ergo/__init__.py
ergo/clumps.py
ergo/core.py
ergo/entities.py
ergo/entity.py
ergo/errors.py
ergo/misc.py
ergo/simple.py
jeffrey/__init__.py
jeffrey/clumps.py
jeffrey/core.py
jeffrey/entities.py
jeffrey/errors.py
jeffrey/misc.py
jeffrey/simple.py
joffrey/__init__.py
joffrey/clumps.py
joffrey/core.py
joffrey/entities.py
joffrey/errors.py
joffrey/misc.py
joffrey/simple.py
kizbra/__init__.py
kizbra/clumps.py
kizbra/core.py
kizbra/entities.py
kizbra/errors.py
kizbra/misc.py
kizbra/simple.py
joffrey-0.5.2.dist-info/LICENSE
joffrey-0.5.2.dist-info/METADATA
joffrey-0.5.2.dist-info/WHEEL
joffrey-0.5.2.dist-info/top_level.txt
joffrey-0.5.2.dist-info/RECORD
