Metadata-Version: 2.1
Name: joffrey
Version: 0.5.2
Summary: A powerful Python 3 command-line parser
Home-page: https://github.com/supposedly/joffrey
Author: Hadi Tarhini
Author-email: eltrhn@gmail.com
License: MIT
Keywords: argparse argument parsing
Platform: UNKNOWN
Classifier: Programming Language :: Python :: 3.5
Classifier: Programming Language :: Python :: 3.6
Classifier: License :: OSI Approved :: MIT License
Classifier: Operating System :: OS Independent
Requires-Python: >=3.5
